artifactdetection/__init__.py
artifactdetection/analyse.py
artifactdetection/explore.py
artifactdetection/implement.py
artifactdetection/load.py
artifactdetection/noisefilter.py
artifactdetection/preprocess.py
tests/__init__.py
tests/test_analyse.py
tests/test_explore.py
tests/test_load.py
tests/test_noisefilter.py
ArtifactDetection-0.0.1.dist-info/LICENSE.md
ArtifactDetection-0.0.1.dist-info/METADATA
ArtifactDetection-0.0.1.dist-info/WHEEL
ArtifactDetection-0.0.1.dist-info/top_level.txt
ArtifactDetection-0.0.1.dist-info/RECORD
